{
  "_class": "shapeGroup",
  "booleanOperation": -1,
  "clippingMaskMode": 0,
  "do_objectID": "6104BD06-C922-4D0F-B796-B79A718162E1",
  "exportOptions": {
    "_class": "exportOptions",
    "do_objectID": "A77623BF-1834-4042-A8BF-4B8080B7E629",
    "exportFormats": [
    ],
    "includedLayerIds": [
    ],
    "layerOptions": 0,
    "shouldTrim": false
  },
  "frame": {
    "_class": "rect",
    "constrainProportions": false,
    "do_objectID": "EDB8D3D1-0781-4D0B-8F33-E32B55E3E2BB",
    "height": 256.7368788669067,
    "width": 259.2370387240906,
    "x": 0.2611005291005108,
    "y": 0.8657906924460191
  },
  "hasClickThrough": false,
  "hasClippingMask": true,
  "isFixedToViewport": false,
  "isFlippedHorizontal": false,
  "isFlippedVertical": false,
  "isLocked": false,
  "isVisible": true,
  "layerListExpandedType": 1,
  "layers": [
    {
      "class": "shapePath",
      "id": "0FD14976-BBF1-4A7A-9EEB-DE93E35A1A7E"
    }
  ],
  "name": "Clip 143",
  "nameIsFixed": false,
  "resizingConstraint": 63,
  "resizingType": 0,
  "rotation": 0,
  "shouldBreakMaskChain": false,
  "style": {
    "_class": "style",
    "do_objectID": "B6A2C736-766E-437C-8A81-7A0B5E161E86",
    "endMarkerType": 0,
    "miterLimit": 10,
    "startMarkerType": 0,
    "windingRule": 1
  },
  "windingRule": 1
}