{
  "_class": "group",
  "booleanOperation": -1,
  "clippingMaskMode": 0,
  "do_objectID": "6C86C1FE-81FB-40FB-8CD2-2FDF198A897C",
  "exportOptions": {
    "_class": "exportOptions",
    "do_objectID": "14615906-7BA3-445C-AF7E-E0F709FCE6B7",
    "exportFormats": [
    ],
    "includedLayerIds": [
    ],
    "layerOptions": 0,
    "shouldTrim": false
  },
  "frame": {
    "_class": "rect",
    "constrainProportions": false,
    "do_objectID": "045F9FB2-5112-42CC-86A2-B1AEB294665B",
    "height": 231.0000000000001,
    "width": 234.0000000000002,
    "x": 0,
    "y": 0
  },
  "hasClickThrough": false,
  "hasClippingMask": false,
  "isFixedToViewport": false,
  "isFlippedHorizontal": false,
  "isFlippedVertical": false,
  "isLocked": false,
  "isVisible": true,
  "layerListExpandedType": 0,
  "layers": [
    {
      "class": "shapeGroup",
      "id": "A0ADBA50-944F-4191-A1D6-EF1ABE23EEB2"
    },
    {
      "class": "shapeGroup",
      "id": "4EBC05A7-CE26-412F-A59F-150D7205FEBA"
    }
  ],
  "name": "Group 1057",
  "nameIsFixed": false,
  "resizingConstraint": 63,
  "resizingType": 0,
  "rotation": 0,
  "shouldBreakMaskChain": false,
  "style": {
    "_class": "style",
    "do_objectID": "8CE30B81-C344-418A-9E24-0218FF6CF742",
    "endMarkerType": 0,
    "miterLimit": 10,
    "startMarkerType": 0,
    "windingRule": 1
  }
}