{
  "_class": "group",
  "booleanOperation": -1,
  "clippingMaskMode": 0,
  "do_objectID": "D969FE83-A686-43C6-8B31-91F7B4C394FF",
  "exportOptions": {
    "_class": "exportOptions",
    "do_objectID": "5AD13386-26C9-4346-9526-710790C9A709",
    "exportFormats": [
    ],
    "includedLayerIds": [
    ],
    "layerOptions": 0,
    "shouldTrim": false
  },
  "frame": {
    "_class": "rect",
    "constrainProportions": false,
    "do_objectID": "F0C5B937-B6A8-4631-9BB5-690B40D60911",
    "height": 223,
    "width": 225.0000000000002,
    "x": 0,
    "y": 0
  },
  "hasClickThrough": false,
  "hasClippingMask": false,
  "isFixedToViewport": false,
  "isFlippedHorizontal": false,
  "isFlippedVertical": false,
  "isLocked": false,
  "isVisible": true,
  "layerListExpandedType": 0,
  "layers": [
    {
      "class": "shapeGroup",
      "id": "69284117-552D-45EB-A396-B9EADE34C3A1"
    },
    {
      "class": "shapeGroup",
      "id": "29647F84-3AA4-49EE-BD21-376353212F9A"
    }
  ],
  "name": "Group 405",
  "nameIsFixed": false,
  "resizingConstraint": 63,
  "resizingType": 0,
  "rotation": 0,
  "shouldBreakMaskChain": false,
  "style": {
    "_class": "style",
    "do_objectID": "02EDBE35-933E-48D3-A305-67A169037A7D",
    "endMarkerType": 0,
    "miterLimit": 10,
    "startMarkerType": 0,
    "windingRule": 1
  }
}