{
  "_class": "shapeGroup",
  "booleanOperation": -1,
  "clippingMaskMode": 0,
  "do_objectID": "D5922F8F-D11D-43F4-AA00-788A74BE24F7",
  "exportOptions": {
    "_class": "exportOptions",
    "do_objectID": "E2E60710-8123-465F-845D-E8407615AC24",
    "exportFormats": [
    ],
    "includedLayerIds": [
    ],
    "layerOptions": 0,
    "shouldTrim": false
  },
  "frame": {
    "_class": "rect",
    "constrainProportions": false,
    "do_objectID": "4855623B-0907-440A-B2D6-D5A460DD3FF6",
    "height": 230.6227350309592,
    "width": 233.3133348516813,
    "x": 0.2349904761904568,
    "y": 0.02034922971459116
  },
  "hasClickThrough": false,
  "hasClippingMask": true,
  "isFixedToViewport": false,
  "isFlippedHorizontal": false,
  "isFlippedVertical": false,
  "isLocked": false,
  "isVisible": true,
  "layerListExpandedType": 1,
  "layers": [
    {
      "class": "shapePath",
      "id": "042B100B-B291-4A40-870F-B4E2DC8B35B8"
    }
  ],
  "name": "Clip 738",
  "nameIsFixed": false,
  "resizingConstraint": 63,
  "resizingType": 0,
  "rotation": 0,
  "shouldBreakMaskChain": false,
  "style": {
    "_class": "style",
    "do_objectID": "2D26A0D0-FB81-491C-8E1F-91D61F166244",
    "endMarkerType": 0,
    "miterLimit": 10,
    "startMarkerType": 0,
    "windingRule": 1
  },
  "windingRule": 1
}