{
  "_class": "shapeGroup",
  "booleanOperation": -1,
  "clippingMaskMode": 0,
  "do_objectID": "A9348B51-2929-4A6B-BDC3-710843BA13F7",
  "exportOptions": {
    "_class": "exportOptions",
    "do_objectID": "8E026E83-D835-4DA5-8AEE-D771404BBBF2",
    "exportFormats": [
    ],
    "includedLayerIds": [
    ],
    "layerOptions": 0,
    "shouldTrim": false
  },
  "frame": {
    "_class": "rect",
    "constrainProportions": false,
    "do_objectID": "C8CD7F0A-5603-4E64-9656-7D868701A079",
    "height": 230.6227350309592,
    "width": 233.3133348516813,
    "x": 0.2349904761904568,
    "y": 0.02034922971459116
  },
  "hasClickThrough": false,
  "hasClippingMask": true,
  "isFixedToViewport": false,
  "isFlippedHorizontal": false,
  "isFlippedVertical": false,
  "isLocked": false,
  "isVisible": true,
  "layerListExpandedType": 1,
  "layers": [
    {
      "class": "shapePath",
      "id": "FEB01048-59EF-4D51-A224-E37757FBB875"
    }
  ],
  "name": "Clip 491",
  "nameIsFixed": false,
  "resizingConstraint": 63,
  "resizingType": 0,
  "rotation": 0,
  "shouldBreakMaskChain": false,
  "style": {
    "_class": "style",
    "do_objectID": "7851CDB4-DBCA-440C-910A-B1912DC52F72",
    "endMarkerType": 0,
    "miterLimit": 10,
    "startMarkerType": 0,
    "windingRule": 1
  },
  "windingRule": 1
}