{
  "_class": "shapeGroup",
  "booleanOperation": -1,
  "clippingMaskMode": 0,
  "do_objectID": "A0FE5DAA-548B-46B7-BF18-5FA090B3484E",
  "exportOptions": {
    "_class": "exportOptions",
    "do_objectID": "1F8175AC-58F0-42DA-862E-A99ECCE1D40A",
    "exportFormats": [
    ],
    "includedLayerIds": [
    ],
    "layerOptions": 0,
    "shouldTrim": false
  },
  "frame": {
    "_class": "rect",
    "constrainProportions": false,
    "do_objectID": "F2C2382F-4310-4617-A5EE-84AA1242931A",
    "height": 5.4764088991314,
    "width": 4.462597115553507,
    "x": 90.37120986496457,
    "y": 197.1543265210478
  },
  "hasClickThrough": false,
  "hasClippingMask": false,
  "isFixedToViewport": false,
  "isFlippedHorizontal": false,
  "isFlippedVertical": false,
  "isLocked": false,
  "isVisible": true,
  "layerListExpandedType": 1,
  "layers": [
    {
      "class": "shapePath",
      "id": "68E1FEA2-3E33-45FB-A6F5-4E60A008A7F6"
    },
    {
      "class": "shapePath",
      "id": "ACFA8832-0376-4683-840C-E14F5FCB1101"
    }
  ],
  "name": "Fill 259",
  "nameIsFixed": false,
  "resizingConstraint": 63,
  "resizingType": 0,
  "rotation": 0,
  "shouldBreakMaskChain": false,
  "style": {
    "_class": "style",
    "do_objectID": "F06CAD48-1EF7-4C82-B789-D26B94BAA464",
    "endMarkerType": 0,
    "fills": [
      {
        "_class": "fill",
        "color": {
          "_class": "color",
          "alpha": 1,
          "blue": 0.224,
          "green": 0.09,
          "red": 0.259
        },
        "fillType": 0,
        "isEnabled": true,
        "noiseIndex": 0,
        "noiseIntensity": 0,
        "patternFillType": 1,
        "patternTileScale": 1
      }
    ],
    "miterLimit": 10,
    "startMarkerType": 0,
    "windingRule": 1
  },
  "windingRule": 1
}