{
  "_class": "shapeGroup",
  "booleanOperation": -1,
  "clippingMaskMode": 0,
  "do_objectID": "49F8283E-26B5-437C-8CFE-0DECBE7360D5",
  "exportOptions": {
    "_class": "exportOptions",
    "do_objectID": "89A6C4E0-D58E-4F47-AA24-55C981246952",
    "exportFormats": [
    ],
    "includedLayerIds": [
    ],
    "layerOptions": 0,
    "shouldTrim": false
  },
  "frame": {
    "_class": "rect",
    "constrainProportions": false,
    "do_objectID": "3F004868-B5F6-416F-885A-3E8316CF9B81",
    "height": 4.454403013025939,
    "width": 3.627054376972609,
    "x": 116.189594140463,
    "y": 178.8591160503932
  },
  "hasClickThrough": false,
  "hasClippingMask": false,
  "isFixedToViewport": false,
  "isFlippedHorizontal": false,
  "isFlippedVertical": false,
  "isLocked": false,
  "isVisible": true,
  "layerListExpandedType": 1,
  "layers": [
    {
      "class": "shapePath",
      "id": "F4D719B5-5265-4497-AF0A-DB1CFB45A714"
    },
    {
      "class": "shapePath",
      "id": "09C92459-E618-4C90-A0DE-52DB859A9A59"
    }
  ],
  "name": "Fill 388",
  "nameIsFixed": false,
  "resizingConstraint": 63,
  "resizingType": 0,
  "rotation": 0,
  "shouldBreakMaskChain": false,
  "style": {
    "_class": "style",
    "do_objectID": "9D1252CB-6CFD-403C-A933-C51DFFCB6695",
    "endMarkerType": 0,
    "fills": [
      {
        "_class": "fill",
        "color": {
          "_class": "color",
          "alpha": 1,
          "blue": 0.224,
          "green": 0.09,
          "red": 0.259
        },
        "fillType": 0,
        "isEnabled": true,
        "noiseIndex": 0,
        "noiseIntensity": 0,
        "patternFillType": 1,
        "patternTileScale": 1
      }
    ],
    "miterLimit": 10,
    "startMarkerType": 0,
    "windingRule": 1
  },
  "windingRule": 1
}