{
  "_class": "group",
  "booleanOperation": -1,
  "clippingMaskMode": 0,
  "do_objectID": "64C86616-8367-454E-BE6D-FE55C43E70EF",
  "exportOptions": {
    "_class": "exportOptions",
    "do_objectID": "48371AB6-7130-47D6-B10D-3AE6033924FE",
    "exportFormats": [
    ],
    "includedLayerIds": [
    ],
    "layerOptions": 0,
    "shouldTrim": false
  },
  "frame": {
    "_class": "rect",
    "constrainProportions": false,
    "do_objectID": "3E2B206A-47EB-49A7-84C5-A68C803618EC",
    "height": 231.0000000000001,
    "width": 234.0000000000002,
    "x": 0,
    "y": 0
  },
  "hasClickThrough": false,
  "hasClippingMask": false,
  "isFixedToViewport": false,
  "isFlippedHorizontal": false,
  "isFlippedVertical": false,
  "isLocked": false,
  "isVisible": true,
  "layerListExpandedType": 0,
  "layers": [
    {
      "class": "shapeGroup",
      "id": "2EE9C2E1-3DE9-4BE4-9573-00221BD5CDC7"
    },
    {
      "class": "shapeGroup",
      "id": "EAF37C76-4A87-4856-A51B-9B040CBFBAED"
    }
  ],
  "name": "Group 844",
  "nameIsFixed": false,
  "resizingConstraint": 63,
  "resizingType": 0,
  "rotation": 0,
  "shouldBreakMaskChain": false,
  "style": {
    "_class": "style",
    "do_objectID": "52D1FF64-9A83-45BC-89F1-17A61CEDACA3",
    "endMarkerType": 0,
    "miterLimit": 10,
    "startMarkerType": 0,
    "windingRule": 1
  }
}