{
  "_class": "text",
  "attributedString": {
    "_class": "attributedString",
    "attributes": [
      {
        "_class": "stringAttribute",
        "attributes": {
          "MSAttributedStringColorAttribute": {
            "_class": "color",
            "alpha": 1,
            "blue": 0.2902374565601349,
            "green": 0.2901752889156342,
            "red": 0.290221631526947
          },
          "MSAttributedStringFontAttribute": {
            "_class": "fontDescriptor",
            "attributes": {
              "name": "SFProDisplay-LightItalic",
              "size": 44
            }
          },
          "paragraphStyle": {
            "_class": "paragraphStyle",
            "maximumLineHeight": 51,
            "minimumLineHeight": 51
          }
        },
        "length": 88,
        "location": 0
      }
    ],
    "string": "Alongside my clients, I uncover problems and help solve them with knowledge and passion."
  },
  "automaticallyDrawOnUnderlyingPath": false,
  "booleanOperation": -1,
  "clippingMaskMode": 0,
  "do_objectID": "950D3DB6-F75C-4D21-8C11-E5CAB99FA4E4",
  "dontSynchroniseWithSymbol": false,
  "exportOptions": {
    "_class": "exportOptions",
    "exportFormats": [
    ],
    "includedLayerIds": [
    ],
    "layerOptions": 0,
    "shouldTrim": false
  },
  "frame": {
    "_class": "rect",
    "constrainProportions": false,
    "height": 206,
    "width": 439,
    "x": 709,
    "y": 477
  },
  "glyphBounds": "{{-2, 9}, {436, 194}}",
  "hasClippingMask": false,
  "isFixedToViewport": false,
  "isFlippedHorizontal": false,
  "isFlippedVertical": false,
  "isLocked": false,
  "isVisible": true,
  "layerListExpandedType": 0,
  "lineSpacingBehaviour": 2,
  "name": "Alongside my clients",
  "nameIsFixed": false,
  "resizingConstraint": 47,
  "resizingType": 0,
  "rotation": 0,
  "sharedStyleID": "975BFBF1-80AE-413D-A348-0FE98793DD16",
  "shouldBreakMaskChain": false,
  "style": {
    "_class": "style",
    "do_objectID": "B8222A39-5EEA-4670-BBCC-9B196122E860",
    "endMarkerType": 0,
    "miterLimit": 10,
    "startMarkerType": 0,
    "textStyle": {
      "_class": "textStyle",
      "encodedAttributes": {
        "MSAttributedStringColorAttribute": {
          "_class": "color",
          "alpha": 1,
          "blue": 0.2902374565601349,
          "green": 0.2901752889156342,
          "red": 0.290221631526947
        },
        "MSAttributedStringFontAttribute": {
          "_class": "fontDescriptor",
          "attributes": {
            "name": "SFProDisplay-LightItalic",
            "size": 44
          }
        },
        "paragraphStyle": {
          "_class": "paragraphStyle",
          "maximumLineHeight": 51,
          "minimumLineHeight": 51
        }
      },
      "verticalAlignment": 0
    },
    "windingRule": 1
  },
  "textBehaviour": 2
}