{
  "_class": "shapePath",
  "booleanOperation": -1,
  "clippingMaskMode": 0,
  "do_objectID": "9423D5F9-850A-4BF5-B1BA-EA80574936C8",
  "edited": true,
  "exportOptions": {
    "_class": "exportOptions",
    "do_objectID": "2B600621-886F-48AF-A81C-AEAE681178A6",
    "exportFormats": [
    ],
    "includedLayerIds": [
    ],
    "layerOptions": 0,
    "shouldTrim": false
  },
  "frame": {
    "_class": "rect",
    "constrainProportions": false,
    "do_objectID": "AC6359CA-0A8F-47D0-B7B6-2639A69F8D2B",
    "height": 1.962857927241125,
    "width": 5.012309705423085,
    "x": 0,
    "y": 0
  },
  "hasClippingMask": false,
  "isClosed": false,
  "isFixedToViewport": false,
  "isFlippedHorizontal": false,
  "isFlippedVertical": false,
  "isLocked": false,
  "isVisible": true,
  "layerListExpandedType": 0,
  "name": "Path",
  "nameIsFixed": false,
  "pointRadiusBehaviour": 1,
  "points": [
    {
      "_class": "curvePoint",
      "cornerRadius": 0,
      "curveFrom": "{1.0121260368716387, 0.10197847385207147}",
      "curveMode": 4,
      "curveTo": "{0.86352426662743154, 0.068289156597366396}",
      "hasCurveFrom": true,
      "hasCurveTo": false,
      "point": "{0.86352426662743154, 0.068289156597366396}"
    },
    {
      "_class": "curvePoint",
      "cornerRadius": 0,
      "curveFrom": "{0.77957855507120821, 1.1281368669884542}",
      "curveMode": 3,
      "curveTo": "{1.0339162002968736, 0.20122538144023536}",
      "hasCurveFrom": true,
      "hasCurveTo": true,
      "point": "{0.95532872564849469, 0.48712931706119211}"
    },
    {
      "_class": "curvePoint",
      "cornerRadius": 0,
      "curveFrom": "{-0.035587886508798607, 0.31686168661176717}",
      "curveMode": 3,
      "curveTo": "{0.24018270634823874, 1.1800366260024526}",
      "hasCurveFrom": true,
      "hasCurveTo": true,
      "point": "{0.046928961871997812, 0.57636048168175946}"
    },
    {
      "_class": "curvePoint",
      "cornerRadius": 0,
      "curveFrom": "{0.3587783499085232, 0.6774284334458488}",
      "curveMode": 4,
      "curveTo": "{-0.0095111335572932911, 0.1292941364910051}",
      "hasCurveFrom": true,
      "hasCurveTo": true,
      "point": "{0.12694529969580362, 0}"
    },
    {
      "_class": "curvePoint",
      "cornerRadius": 0,
      "curveFrom": "{0.86352426662743154, 0.068289156597366396}",
      "curveMode": 4,
      "curveTo": "{0.6291907058577163, 0.70292305190886994}",
      "hasCurveFrom": false,
      "hasCurveTo": true,
      "point": "{0.86352426662743154, 0.068289156597366396}"
    }
  ],
  "resizingConstraint": 63,
  "resizingType": 0,
  "rotation": 0,
  "shouldBreakMaskChain": false,
  "style": {
    "_class": "style",
    "do_objectID": "EB4CF902-9D9B-413C-BAE3-46B080692B6E",
    "endMarkerType": 0,
    "miterLimit": 10,
    "startMarkerType": 0,
    "windingRule": 1
  }
}