{
  "_class": "group",
  "booleanOperation": -1,
  "clippingMaskMode": 0,
  "do_objectID": "E6AD2DC8-0C0E-444E-B2C2-D4014127529F",
  "exportOptions": {
    "_class": "exportOptions",
    "do_objectID": "C497DFE5-4E34-414A-826A-34BEFE7EF7ED",
    "exportFormats": [
    ],
    "includedLayerIds": [
    ],
    "layerOptions": 0,
    "shouldTrim": false
  },
  "frame": {
    "_class": "rect",
    "constrainProportions": false,
    "do_objectID": "36E913DD-3FEC-48BA-A7D9-F537FE920CAE",
    "height": 258,
    "width": 260,
    "x": 0,
    "y": 0
  },
  "hasClickThrough": false,
  "hasClippingMask": false,
  "isFixedToViewport": false,
  "isFlippedHorizontal": false,
  "isFlippedVertical": false,
  "isLocked": false,
  "isVisible": true,
  "layerListExpandedType": 0,
  "layers": [
    {
      "class": "shapeGroup",
      "id": "B8647D28-7E65-4FF8-8D13-F31320B2D897"
    },
    {
      "class": "shapeGroup",
      "id": "C0D3C6DA-53D7-4D8B-89D9-E33B32327AFE"
    }
  ],
  "name": "Group 156",
  "nameIsFixed": false,
  "resizingConstraint": 63,
  "resizingType": 0,
  "rotation": 0,
  "shouldBreakMaskChain": false,
  "style": {
    "_class": "style",
    "do_objectID": "40076D45-8DF7-4AA4-A187-6F0ECA6A1EE6",
    "endMarkerType": 0,
    "miterLimit": 10,
    "startMarkerType": 0,
    "windingRule": 1
  }
}