{
  "_class": "shapeGroup",
  "booleanOperation": -1,
  "clippingMaskMode": 0,
  "do_objectID": "852E7B4D-03C9-4C31-ACF0-02F0DD386B52",
  "exportOptions": {
    "_class": "exportOptions",
    "do_objectID": "A2FDA42B-4031-46ED-8BD8-BD6C52E3B88E",
    "exportFormats": [
    ],
    "includedLayerIds": [
    ],
    "layerOptions": 0,
    "shouldTrim": false
  },
  "frame": {
    "_class": "rect",
    "constrainProportions": false,
    "do_objectID": "AF9E28F2-3A91-4D2E-B61D-9C8F1FE61F18",
    "height": 256.7368788669067,
    "width": 259.2370387240906,
    "x": 0.2611005291005108,
    "y": 0.8657906924460191
  },
  "hasClickThrough": false,
  "hasClippingMask": true,
  "isFixedToViewport": false,
  "isFlippedHorizontal": false,
  "isFlippedVertical": false,
  "isLocked": false,
  "isVisible": true,
  "layerListExpandedType": 1,
  "layers": [
    {
      "class": "shapePath",
      "id": "417F06B0-B6C1-4DF6-9F58-E24C62954AD8"
    }
  ],
  "name": "Clip 473",
  "nameIsFixed": false,
  "resizingConstraint": 63,
  "resizingType": 0,
  "rotation": 0,
  "shouldBreakMaskChain": false,
  "style": {
    "_class": "style",
    "do_objectID": "94A84E52-3413-4BD9-BA02-81E070671AA2",
    "endMarkerType": 0,
    "miterLimit": 10,
    "startMarkerType": 0,
    "windingRule": 1
  },
  "windingRule": 1
}