{
  "_class": "shapeGroup",
  "booleanOperation": -1,
  "clippingMaskMode": 0,
  "do_objectID": "81C0FA38-B327-462D-8475-946EDF2A8531",
  "exportOptions": {
    "_class": "exportOptions",
    "do_objectID": "BF93F937-1D08-4575-9F10-47790684EE42",
    "exportFormats": [
    ],
    "includedLayerIds": [
    ],
    "layerOptions": 0,
    "shouldTrim": false
  },
  "frame": {
    "_class": "rect",
    "constrainProportions": false,
    "do_objectID": "77B54ECC-BF64-44F1-AD45-92DD3E6E072A",
    "height": 283.5361764016987,
    "width": 287.1548736636078,
    "x": 0.2892190476190238,
    "y": 0.02501810060148869
  },
  "hasClickThrough": false,
  "hasClippingMask": true,
  "isFixedToViewport": false,
  "isFlippedHorizontal": false,
  "isFlippedVertical": false,
  "isLocked": false,
  "isVisible": true,
  "layerListExpandedType": 1,
  "layers": [
    {
      "class": "shapePath",
      "id": "348755D3-D8DB-4BE2-9C4F-1082C9352829"
    }
  ],
  "name": "Clip 389",
  "nameIsFixed": false,
  "resizingConstraint": 63,
  "resizingType": 0,
  "rotation": 0,
  "shouldBreakMaskChain": false,
  "style": {
    "_class": "style",
    "do_objectID": "62506AE8-5E6A-41B8-9BFF-62B3ED7B89F0",
    "endMarkerType": 0,
    "miterLimit": 10,
    "startMarkerType": 0,
    "windingRule": 1
  },
  "windingRule": 1
}