{
  "_class": "group",
  "booleanOperation": -1,
  "clippingMaskMode": 0,
  "do_objectID": "079A682A-07F1-4B9E-B076-2AEB78D2AD99",
  "exportOptions": {
    "_class": "exportOptions",
    "do_objectID": "CB189F49-DA8F-49C0-BE00-E3460D9233AC",
    "exportFormats": [
    ],
    "includedLayerIds": [
    ],
    "layerOptions": 0,
    "shouldTrim": false
  },
  "frame": {
    "_class": "rect",
    "constrainProportions": false,
    "do_objectID": "A5FF444B-2B1B-4F9F-B65C-F3B6339C003D",
    "height": 284,
    "width": 288.0000000000002,
    "x": 0,
    "y": 0
  },
  "hasClickThrough": false,
  "hasClippingMask": false,
  "isFixedToViewport": false,
  "isFlippedHorizontal": false,
  "isFlippedVertical": false,
  "isLocked": false,
  "isVisible": true,
  "layerListExpandedType": 0,
  "layers": [
    {
      "class": "shapeGroup",
      "id": "2F3D3820-8983-49E5-B7CE-18E85B7306AE"
    },
    {
      "class": "shapeGroup",
      "id": "25448F7B-D1CC-4F18-9FAA-92585B1EC610"
    }
  ],
  "name": "Group 832",
  "nameIsFixed": false,
  "resizingConstraint": 63,
  "resizingType": 0,
  "rotation": 0,
  "shouldBreakMaskChain": false,
  "style": {
    "_class": "style",
    "do_objectID": "4F2CFC50-6318-437B-A40E-F36CA3995AC2",
    "endMarkerType": 0,
    "miterLimit": 10,
    "startMarkerType": 0,
    "windingRule": 1
  }
}