{
  "_class": "shapePath",
  "booleanOperation": -1,
  "clippingMaskMode": 0,
  "do_objectID": "60054D26-53BD-408D-971D-736521D4E917",
  "edited": true,
  "exportOptions": {
    "_class": "exportOptions",
    "exportFormats": [
    ],
    "includedLayerIds": [
    ],
    "layerOptions": 0,
    "shouldTrim": false
  },
  "frame": {
    "_class": "rect",
    "constrainProportions": false,
    "height": 5.687500000000028,
    "width": 4.467901234567876,
    "x": 166.9528753086421,
    "y": 215.73478125
  },
  "hasClippingMask": false,
  "isClosed": true,
  "isFixedToViewport": false,
  "isFlippedHorizontal": false,
  "isFlippedVertical": false,
  "isLocked": false,
  "isVisible": true,
  "layerListExpandedType": 0,
  "name": "Fill 241",
  "nameIsFixed": false,
  "pointRadiusBehaviour": 1,
  "points": [
    {
      "_class": "curvePoint",
      "cornerRadius": 0,
      "curveFrom": "{0.22727272727272699, 0.17857142857142874}",
      "curveMode": 1,
      "curveTo": "{0.22727272727272699, 0.17857142857142874}",
      "hasCurveFrom": false,
      "hasCurveTo": false,
      "point": "{0.22727272727272699, 0.17857142857142874}"
    },
    {
      "_class": "curvePoint",
      "cornerRadius": 0,
      "curveFrom": "{0.22727272727272699, 0.17857142857142874}",
      "curveMode": 1,
      "curveTo": "{0.22727272727272699, 0.17857142857142874}",
      "hasCurveFrom": false,
      "hasCurveTo": false,
      "point": "{0.22727272727272699, 0.17857142857142874}"
    },
    {
      "_class": "curvePoint",
      "cornerRadius": 0,
      "curveFrom": "{0.090909090909092077, 0.35714285714285748}",
      "curveMode": 1,
      "curveTo": "{0.090909090909092077, 0.35714285714285748}",
      "hasCurveFrom": false,
      "hasCurveTo": false,
      "point": "{0.090909090909092077, 0.35714285714285748}"
    },
    {
      "_class": "curvePoint",
      "cornerRadius": 0,
      "curveFrom": "{0, 0.28571428571428498}",
      "curveMode": 1,
      "curveTo": "{0, 0.28571428571428498}",
      "hasCurveFrom": false,
      "hasCurveTo": false,
      "point": "{0, 0.28571428571428498}"
    },
    {
      "_class": "curvePoint",
      "cornerRadius": 0,
      "curveFrom": "{0.18136363636363653, 0.071428571428572521}",
      "curveMode": 1,
      "curveTo": "{0.18136363636363653, 0.071428571428572521}",
      "hasCurveFrom": false,
      "hasCurveTo": false,
      "point": "{0.18136363636363653, 0.071428571428572521}"
    },
    {
      "_class": "curvePoint",
      "cornerRadius": 0,
      "curveFrom": "{0.31818181818181906, 0}",
      "curveMode": 1,
      "curveTo": "{0.31818181818181906, 0}",
      "hasCurveFrom": false,
      "hasCurveTo": false,
      "point": "{0.31818181818181906, 0}"
    },
    {
      "_class": "curvePoint",
      "cornerRadius": 0,
      "curveFrom": "{1, 0.9642857142857163}",
      "curveMode": 1,
      "curveTo": "{1, 0.9642857142857163}",
      "hasCurveFrom": false,
      "hasCurveTo": false,
      "point": "{1, 0.9642857142857163}"
    },
    {
      "_class": "curvePoint",
      "cornerRadius": 0,
      "curveFrom": "{0.81818181818181579, 1}",
      "curveMode": 1,
      "curveTo": "{0.81818181818181579, 1}",
      "hasCurveFrom": false,
      "hasCurveTo": false,
      "point": "{0.81818181818181579, 1}"
    }
  ],
  "resizingConstraint": 63,
  "resizingType": 0,
  "rotation": 0,
  "shouldBreakMaskChain": false,
  "style": {
    "_class": "style",
    "endMarkerType": 0,
    "fills": [
      {
        "_class": "fill",
        "color": {
          "_class": "color",
          "alpha": 1,
          "blue": 0.224,
          "green": 0.09,
          "red": 0.259
        },
        "fillType": 0,
        "isEnabled": true,
        "noiseIndex": 0,
        "noiseIntensity": 0,
        "patternFillType": 1,
        "patternTileScale": 1
      }
    ],
    "miterLimit": 10,
    "startMarkerType": 0,
    "windingRule": 1
  }
}